helios/__init__.py
olmoearth_pretrain/__init__.py
olmoearth_pretrain/_compat.py
olmoearth_pretrain/config.py
olmoearth_pretrain/datatypes.py
olmoearth_pretrain/decorators.py
olmoearth_pretrain/model_loader.py
olmoearth_pretrain/types.py
olmoearth_pretrain/data/__init__.py
olmoearth_pretrain/data/concat.py
olmoearth_pretrain/data/constants.py
olmoearth_pretrain/data/dataloader.py
olmoearth_pretrain/data/dataset.py
olmoearth_pretrain/data/normalize.py
olmoearth_pretrain/data/transform.py
olmoearth_pretrain/data/utils.py
olmoearth_pretrain/data/visualize.py
olmoearth_pretrain/data/norm_configs/computed.json
olmoearth_pretrain/data/norm_configs/predefined.json
olmoearth_pretrain/dataset/__init__.py
olmoearth_pretrain/dataset/convert_to_h5py.py
olmoearth_pretrain/dataset/parse.py
olmoearth_pretrain/dataset/sample.py
olmoearth_pretrain/dataset/utils.py
olmoearth_pretrain/dataset_creation/__init__.py
olmoearth_pretrain/dataset_creation/constants.py
olmoearth_pretrain/dataset_creation/make_meta_summary.py
olmoearth_pretrain/dataset_creation/util.py
olmoearth_pretrain/dataset_creation/create_windows/__init__.py
olmoearth_pretrain/dataset_creation/create_windows/from_lon_lat_list.py
olmoearth_pretrain/dataset_creation/create_windows/random.py
olmoearth_pretrain/dataset_creation/create_windows/util.py
olmoearth_pretrain/dataset_creation/openstreetmap/osm_tiles_by_category_to_lonlats.py
olmoearth_pretrain/dataset_creation/rslearn_to_olmoearth/__init__.py
olmoearth_pretrain/dataset_creation/rslearn_to_olmoearth/cdl.py
olmoearth_pretrain/dataset_creation/rslearn_to_olmoearth/era5.py
olmoearth_pretrain/dataset_creation/rslearn_to_olmoearth/era5_10.py
olmoearth_pretrain/dataset_creation/rslearn_to_olmoearth/gse.py
olmoearth_pretrain/dataset_creation/rslearn_to_olmoearth/landsat.py
olmoearth_pretrain/dataset_creation/rslearn_to_olmoearth/multitemporal_raster.py
olmoearth_pretrain/dataset_creation/rslearn_to_olmoearth/naip.py
olmoearth_pretrain-0.0.2.dist-info/licenses/LICENSE
olmoearth_pretrain-0.0.2.dist-info/METADATA
olmoearth_pretrain-0.0.2.dist-info/WHEEL
olmoearth_pretrain-0.0.2.dist-info/top_level.txt
olmoearth_pretrain-0.0.2.dist-info/RECORD
