Metadata-Version: 2.4
Name: olmoearth-pretrain
Version: 0.0.2
Summary: A library for developing earth system foundation models
Author: OlmoEarth Team
License: OlmoEarth Artifact License
Requires-Python: <3.14,>=3.11
License-File: LICENSE
Requires-Dist: einops>=0.7.0
Requires-Dist: huggingface_hub
Requires-Dist: numpy>=1.26.4
Requires-Dist: torch<2.8,>=2.7
Requires-Dist: universal-pathlib>=0.2.5
Dynamic: license-file
